sheetconf/__init__.py
sheetconf/cli.py
sheetconf/exceptions.py
sheetconf/langhelpers.py
sheetconf/py.typed
sheetconf/types.py
sheetconf/usegspread.py
sheetconf/usepydantic.py
sheetconf-0.0.1.dist-info/METADATA
sheetconf-0.0.1.dist-info/WHEEL
sheetconf-0.0.1.dist-info/entry_points.txt
sheetconf-0.0.1.dist-info/top_level.txt
sheetconf-0.0.1.dist-info/RECORD
