Metadata-Version: 2.1
Name: sheetconf
Version: 0.0.1
Summary: google spreadsheet as config file
Home-page: https://github.com/podhmo/sheetconf
Author: podhmo
Author-email: ababjam61+github@gmail.com
License: UNKNOWN
Platform: UNKNOWN
Classifier: Programming Language :: Python :: 3
Classifier: Development Status :: 3 - Alpha
Requires-Python: >3.5
Requires-Dist: pydantic
Requires-Dist: gspread
Requires-Dist: typing-extensions
Provides-Extra: dev
Requires-Dist: black ; extra == 'dev'
Requires-Dist: flake8 ; extra == 'dev'
Requires-Dist: mypy ; extra == 'dev'
Provides-Extra: testing
Requires-Dist: pytest ; extra == 'testing'
